{"file_name": "36.docx", "file_type": "docx", "confidence": 0.85, "time_taken": 0.07, "memory_mb": 0.76, "units": [{"type": "paragraph", "text": "ERGEI HCHIPANOV\nI am a Soware Engineer with 6+ years experience in development and\ndesign on a wide technological stack. My main proficiency is building\nhighload Java backends. I design and build crical parts for core business\napplicaons such as integraon buses, CI/CD and infrastructure\napplicaons.\nLooking f or t he S enior S oware E ngineer p osion.\nLanguages: E nglish, H ebrew, R ussian ( nave).\n27 y .o., K far S aba, I srael\nSkills: J ava, J ava 8 , T ypeScript, C ++, C #;\nMaven, G radle, G ulp;\nTel: \nSpring, S pring B oot, N odeJs, A pache C amel, A pache K aa;\nEmail: t \nJUnit, J Unit 5 , M ockito, C ucumber;\nLN: l inkedin.com/in/s-shipanov\nPL S QL, M S S QL, P ostgreSQL; M ongoDB, C ouchbase;\nGit, T FS;\nJenkins, T eamCity; D ocker, K ubernetes;\nAgile, K anban, S crum;\nWork experience\nSogo Services ( Israel, Tel-Aviv) Im w orking a s a S oware E ngineer w ith t he b usiness c rical p rojects o n\nSoware E ngineer a w ide t echnological s tack\nDecember 2 019 - p resent - J ava, T ypeScript, S pring, S pring B oot, N odeJs, A pache K aa\n- V oIP, C IrcleCI, G it\nAmdocs ( Israel, Raanana) I w as d esigning b ackend f or t he t elecom c ompanies c ustomers s upport\nSoware E ngineer applicaon a s a p art o f t he h uge i nternaonal t eam\nJune 2 019 - D ecember 2 019 - J ava, A pache C amel, H ibernate\n- D ocker, J enkins, P erforce\n- C ouchbase, P ostgreSQL\nNexign ( Russia, Moscow) I w as r esponsible f or b uilding t he b ackend f or c ustomer U I u sed i n t op 3\nSenior S oware E ngineer telecom c arriers. I w as a ble t o m ake m ulple i nfrastructure u pdates s uch\nFebruary 2 018 - D ecember 2 018 as p roper c onfiguraon m anagement, e dge i nterfaces a nd A PI r edesign,\nremoving b olenecks i n t he i ntegraon p rocess.\n- J ava, S pring, S pring B oot\n- D ocker, J enkins, T eamCity\n- M ongoDB\nAlfaGroup ( Russia, Moscow) I w as a m ember o f c ore s ervice b us d evelopment t eam\nJava D eveloper - J ava, S pring, R edHat J Boss F use, J enkins\nJune 2 017 - F ebruary 2 018 - M S S QL, P L S QL\nLuxo ( Russia, Moscow) Developed v isual d atabase q uery b uilder a nd r elated t ools.\nJava D eveloper - J ava, E clipse\nOctober 2 014 - J une 2 017 - D B2, J azz, O S Z , J enkins\nEducaon\nMEPhI, Naonal Research Mastrer's ( 2'nd) d egree. F aculty o f C ybernecs, A utomated S ystems.\nNuclear University\n2011  2 016", "confidence": 0.9, "metadata": {"style": "Normal"}}, {"type": "textbox", "text": "ERGEI HCHIPANOV", "confidence": 0.85, "metadata": {}}, {"type": "textbox", "text": "I am a Soware Engineer with 6+ years experience in development and", "confidence": 0.85, "metadata": {}}, {"type": "textbox", "text": "design on a wide technological stack. My main proficiency is building", "confidence": 0.85, "metadata": {}}, {"type": "textbox", "text": "highload Java backends. I design and build crical parts for core business", "confidence": 0.85, "metadata": {}}, {"type": "textbox", "text": "applicaons such as integraon buses, CI/CD and infrastructure", "confidence": 0.85, "metadata": {}}, {"type": "textbox", "text": "applicaons.", "confidence": 0.85, "metadata": {}}, {"type": "textbox", "text": "Looking f or t he S enior S oware E ngineer p osion.", "confidence": 0.85, "metadata": {}}, {"type": "textbox", "text": "Languages: E nglish, H ebrew, R ussian ( nave).", "confidence": 0.85, "metadata": {}}, {"type": "textbox", "text": "27 y .o., K far S aba, I srael", "confidence": 0.85, "metadata": {}}, {"type": "textbox", "text": "Skills: J ava, J ava 8 , T ypeScript, C ++, C #;", "confidence": 0.85, "metadata": {}}, {"type": "textbox", "text": "Maven, G radle, G ulp;", "confidence": 0.85, "metadata": {}}, {"type": "textbox", "text": "Tel:", "confidence": 0.85, "metadata": {}}, {"type": "textbox", "text": "Spring, S pring B oot, N odeJs, A pache C amel, A pache K aa;", "confidence": 0.85, "metadata": {}}, {"type": "textbox", "text": "Email: t", "confidence": 0.85, "metadata": {}}, {"type": "textbox", "text": "JUnit, J Unit 5 , M ockito, C ucumber;", "confidence": 0.85, "metadata": {}}, {"type": "textbox", "text": "LN: l inkedin.com/in/s-shipanov", "confidence": 0.85, "metadata": {}}, {"type": "textbox", "text": "PL S QL, M S S QL, P ostgreSQL; M ongoDB, C ouchbase;", "confidence": 0.85, "metadata": {}}, {"type": "textbox", "text": "Git, T FS;", "confidence": 0.85, "metadata": {}}, {"type": "textbox", "text": "Jenkins, T eamCity; D ocker, K ubernetes;", "confidence": 0.85, "metadata": {}}, {"type": "textbox", "text": "Agile, K anban, S crum;", "confidence": 0.85, "metadata": {}}, {"type": "textbox", "text": "Work experience", "confidence": 0.85, "metadata": {}}, {"type": "textbox", "text": "Sogo Services ( Israel, Tel-Aviv) Im w orking a s a S oware E ngineer w ith t he b usiness c rical p rojects o n", "confidence": 0.85, "metadata": {}}, {"type": "textbox", "text": "Soware E ngineer a w ide t echnological s tack", "confidence": 0.85, "metadata": {}}, {"type": "textbox", "text": "December 2 019 - p resent - J ava, T ypeScript, S pring, S pring B oot, N odeJs, A pache K aa", "confidence": 0.85, "metadata": {}}, {"type": "textbox", "text": "- V oIP, C IrcleCI, G it", "confidence": 0.85, "metadata": {}}, {"type": "textbox", "text": "Amdocs ( Israel, Raanana) I w as d esigning b ackend f or t he t elecom c ompanies c ustomers s upport", "confidence": 0.85, "metadata": {}}, {"type": "textbox", "text": "Soware E ngineer applicaon a s a p art o f t he h uge i nternaonal t eam", "confidence": 0.85, "metadata": {}}, {"type": "textbox", "text": "June 2 019 - D ecember 2 019 - J ava, A pache C amel, H ibernate", "confidence": 0.85, "metadata": {}}, {"type": "textbox", "text": "- D ocker, J enkins, P erforce", "confidence": 0.85, "metadata": {}}, {"type": "textbox", "text": "- C ouchbase, P ostgreSQL", "confidence": 0.85, "metadata": {}}, {"type": "textbox", "text": "Nexign ( Russia, Moscow) I w as r esponsible f or b uilding t he b ackend f or c ustomer U I u sed i n t op 3", "confidence": 0.85, "metadata": {}}, {"type": "textbox", "text": "Senior S oware E ngineer telecom c arriers. I w as a ble t o m ake m ulple i nfrastructure u pdates s uch", "confidence": 0.85, "metadata": {}}, {"type": "textbox", "text": "February 2 018 - D ecember 2 018 as p roper c onfiguraon m anagement, e dge i nterfaces a nd A PI r edesign,", "confidence": 0.85, "metadata": {}}, {"type": "textbox", "text": "removing b olenecks i n t he i ntegraon p rocess.", "confidence": 0.85, "metadata": {}}, {"type": "textbox", "text": "- J ava, S pring, S pring B oot", "confidence": 0.85, "metadata": {}}, {"type": "textbox", "text": "- D ocker, J enkins, T eamCity", "confidence": 0.85, "metadata": {}}, {"type": "textbox", "text": "- M ongoDB", "confidence": 0.85, "metadata": {}}, {"type": "textbox", "text": "AlfaGroup ( Russia, Moscow) I w as a m ember o f c ore s ervice b us d evelopment t eam", "confidence": 0.85, "metadata": {}}, {"type": "textbox", "text": "Java D eveloper - J ava, S pring, R edHat J Boss F use, J enkins", "confidence": 0.85, "metadata": {}}, {"type": "textbox", "text": "June 2 017 - F ebruary 2 018 - M S S QL, P L S QL", "confidence": 0.85, "metadata": {}}, {"type": "textbox", "text": "Luxo ( Russia, Moscow) Developed v isual d atabase q uery b uilder a nd r elated t ools.", "confidence": 0.85, "metadata": {}}, {"type": "textbox", "text": "Java D eveloper - J ava, E clipse", "confidence": 0.85, "metadata": {}}, {"type": "textbox", "text": "October 2 014 - J une 2 017 - D B2, J azz, O S Z , J enkins", "confidence": 0.85, "metadata": {}}, {"type": "textbox", "text": "Educaon", "confidence": 0.85, "metadata": {}}, {"type": "textbox", "text": "MEPhI, Naonal Research Mastrer's ( 2'nd) d egree. F aculty o f C ybernecs, A utomated S ystems.", "confidence": 0.85, "metadata": {}}, {"type": "textbox", "text": "Nuclear University", "confidence": 0.85, "metadata": {}}, {"type": "textbox", "text": "2011  2 016", "confidence": 0.85, "metadata": {}}], "error": null, "embedding": [-0.007743808440864086, 0.047320786863565445, -0.011856270022690296, 0.0022482117637991905, 0.054655175656080246, 0.028590120375156403, 0.028997009620070457, 0.04380379989743233, -0.027866646647453308, -0.029880382120609283, -0.014401447027921677, -0.006158115807920694, -0.08284147083759308, 0.024110224097967148, 7.299621211132035e-05, 0.06008842587471008, 0.04338306561112404, 0.01291031762957573, 0.0169062539935112, -0.03493029624223709, 0.027286311611533165, 0.0069266739301383495, 0.010192782618105412, 0.017590750008821487, 0.021579548716545105, 0.012758396565914154, 0.0032418968621641397, 0.016500307247042656, -0.05789947509765625, -0.017607515677809715, 0.013121053576469421, -0.0027168334927409887, -0.029102422297000885, -0.03763178363442421, -0.021667664870619774, 0.013369952328503132, -0.046782564371824265, 0.0005745701491832733, -0.010462773032486439, 0.0007607682491652668, -0.035186517983675, -0.011541946791112423, -0.0062983836978673935, 0.03416543826460838, -0.04979930445551872, 0.04033390432596207, -0.07650546729564667, 0.028414703905582428, -0.031107677146792412, -0.012226820923388004, -0.0726432204246521, 0.010041117668151855, 0.02486378885805607, 0.002600905718281865, 0.02249802090227604, 0.04928639531135559, 0.03409212827682495, -0.05007893219590187, -0.010032801888883114, -0.013010719791054726, 0.02969708852469921, -0.019556615501642227, 0.0025796014815568924, -0.0018765563145279884, 0.027096223086118698, 0.006319690030068159, -0.0032582159619778395, 0.02764245495200157, -0.03802928701043129, 0.01412668451666832, -0.022006096318364143, -0.001453349948860705, 0.014198233373463154, -0.05542577803134918, 0.038756921887397766, -0.07784239947795868, 0.009938333183526993, 0.05362814664840698, 0.03325934708118439, 0.03767113387584686, 0.011916331015527248, 0.017820121720433235, -0.04141836613416672, 0.05334654450416565, -0.001000109245069325, -0.005964905023574829, -0.023237984627485275, -0.009603826329112053, -0.08889439702033997, 0.03804994001984596, -0.010934725403785706, -0.05084158107638359, 0.05502557381987572, 0.005538506433367729, 0.0279170460999012, -1.5686132428527344e-06, 0.03885124623775482, 0.05142568424344063, 0.028802458196878433, 0.019445087760686874, -0.002351580886170268, -0.033141594380140305, -0.0012462048325687647, -0.023918312042951584, -0.06104710325598717, -0.02399301528930664, -0.014665246941149235, 0.024496495723724365, -0.017059268429875374, 0.012017477303743362, 0.017265409231185913, -0.016437748447060585, -0.02669123373925686, 0.0041013676673173904, -0.061882615089416504, 0.06907979398965836, 0.01795967109501362, -0.04087606817483902, 0.0032860836945474148, -0.020341673865914345, 0.04343007504940033, 0.07001634687185287, -0.007342216093093157, 0.09576340764760971, -0.002047556219622493, 0.02519133873283863, -0.016938654705882072, 0.0590239092707634, -0.0436362698674202, -0.05035780370235443, -0.008179053664207458, 0.07819865643978119, -0.024878090247511864, 0.004362772684544325, -0.004819454625248909, 0.007357476279139519, 0.0424623005092144, -0.012315312400460243, 0.0224368404597044, 0.01245122216641903, -0.005788020323961973, -0.03343908116221428, 0.03702698275446892, -0.02808002568781376, 0.0352548286318779, 0.021332690492272377, 0.006975684314966202, -0.07440345734357834, 0.000815647654235363, 0.01852981001138687, -0.026601441204547882, 0.00983134564012289, 0.011885195970535278, -0.02789582498371601, 0.02131185680627823, 0.026043957099318504, 0.0037428413052111864, -0.0042685456573963165, -0.05112726613879204, -0.007562233600765467, 0.021720385178923607, -0.030554551631212234, 0.011941861361265182, 0.0037857438437640667, -0.02484278567135334, 0.024034902453422546, 0.006563351023942232, 0.008393011055886745, 0.0009640852804295719, 0.0304779764264822, -0.060420453548431396, -0.05732852220535278, 0.046966973692178726, -0.030656950548291206, -0.009737001731991768, -0.009454031474888325, 0.07440013438463211, 0.0016838901210576296, 0.026461314409971237, -0.004793797619640827, -0.05797610431909561, 0.04980258271098137, -0.003294338472187519, -0.020024675875902176, -0.027485717087984085, -0.05879199877381325, 0.03814289718866348, -0.010452885180711746, -0.021017421036958694, -0.005400005262345076, -0.06206852197647095, -0.06235890835523605, 0.020369889214634895, 0.04163259640336037, 0.02302296832203865, -0.030193215236067772, -0.015861952677369118, 0.003850063309073448, -0.0041746338829398155, 0.04265043884515762, 0.006105222273617983, 0.022341128438711166, 0.004416184965521097, -0.034346554428339005, -0.03905656933784485, 0.06843602657318115, 0.0262672808021307, 0.027857627719640732, -0.003845494706183672, 0.034998632967472076, 0.04135565087199211, -0.007772045210003853, 0.04742000252008438, -0.04025282338261604, 0.02866816706955433, 0.030608883127570152, 0.04516136273741722, -0.024399900808930397, 0.03211449831724167, -0.009554240852594376, 0.023747175931930542, -0.01319401990622282, -0.029525795951485634, 0.05866460129618645, 0.006538084242492914, 0.0754924863576889, 0.0705673024058342, -0.07146710157394409, -0.03370586037635803, 0.027199311181902885, 0.027885964140295982, -0.03427141159772873, 0.017668938264250755, 0.029891520738601685, -0.02883807010948658, -0.005510497372597456, -0.015003071166574955, 0.0013693791115656495, 0.05308237671852112, -0.044016316533088684, -0.008461534045636654, 0.10157525539398193, -0.005722410976886749, 0.04178638383746147, 0.025535082444548607, -0.024038352072238922, 0.025530854240059853, -0.04329561069607735, -0.04647373780608177, -0.012231934815645218, -0.026085177436470985, -0.041882436722517014, 0.03236819803714752, -0.07100128382444382, 0.0006410293863154948, -0.08190155774354935, -0.027231279760599136, 0.041856326162815094, 0.04540713131427765, 0.03975486755371094, -0.02826988324522972, 0.01675180159509182, 0.010606512427330017, 0.013548932038247585, 0.0031720120459795, -0.08741443604230881, -0.04159753397107124, 0.007996664382517338, -0.020083386451005936, 0.012961002998054028, 0.008959460072219372, -0.0028149669524282217, 0.020839937031269073, -0.008990345522761345, -0.011180821806192398, -0.016085758805274963, 0.014084897004067898, 0.024297475814819336, -0.0031103689689189196, -0.05580470338463783, 0.01833915524184704, 0.08099040389060974, -0.03445371612906456, -0.03934502229094505, 0.00019539623463060707, -0.060559216886758804, 0.010106760077178478, -0.06353666633367538, -0.019019698724150658, 0.04990149289369583, 0.007532959803938866, 0.06513295322656631, -0.03437693044543266, 0.018188849091529846, 0.06436298042535782, -0.008754533715546131, 0.02136228047311306, 0.0337819904088974, 0.014428817667067051, -0.019427301362156868, 0.0326995849609375, 0.027410784736275673, 0.00900709256529808, 0.034353986382484436, -0.018461892381310463, -0.01468871720135212, 0.06663910299539566, -0.04789552092552185, -0.26566439867019653, -0.003841992700472474, 0.015336784534156322, -0.0324733667075634, 0.04389472305774689, 0.02247139811515808, 0.02052231691777706, -0.020711714401841164, -0.041634079068899155, 0.01153650600463152, -0.054964978247880936, -0.0005081343697384, 0.03501906991004944, 0.05023748800158501, 0.03607965260744095, 0.027053898200392723, 0.04224921017885208, -0.046268265694379807, -0.0005395396146923304, 0.0021699080243706703, -0.03761076182126999, -0.08795364201068878, -0.012317683547735214, 0.01407551672309637, 0.03014563024044037, 0.06149808689951897, -0.06976318359375, 0.006404102314263582, -0.05335800722241402, 0.0060087102465331554, -0.011794880032539368, -0.01484562736004591, -0.0001591965847183019, 0.0027744919061660767, 0.0008775250753387809, -0.01853441819548607, 0.027142254635691643, -0.0075381058268249035, 0.0009200237691402435, -0.02995985560119152, -0.015090360306203365, -0.004420895129442215, -0.05914098024368286, 0.01782454177737236, 0.03745882958173752, -0.024713248014450073, -0.02121717855334282, -0.0019986641127616167, -0.00808851420879364, 0.027129722759127617, 0.0014454828342422843, -0.051195114850997925, 0.0035395186860114336, 0.02078322321176529, -0.0051585473120212555, -0.00950236339122057, -0.006893711164593697, 0.021223030984401703, -0.009160240180790424, 0.00947108305990696, 0.008948721922934055, -0.05096371844410896, -0.0661410316824913, -0.03934865817427635, 0.007767092902213335, -0.05920371785759926, -0.030837005004286766, -0.037392508238554, 0.049267351627349854, 0.017380492761731148, -0.03166019171476364, 0.006681273225694895, 0.0035523860715329647, -0.10180491954088211, 0.027179233729839325, -0.011651953682303429, 0.004854077007621527, -0.018936393782496452, 0.03092150203883648, 0.02552463486790657, -0.022340450435876846, -0.021989936009049416, 0.05432279780507088, 0.03978871926665306, 0.021960433572530746, -0.018682386726140976, 0.011265662498772144, 0.01757989078760147, -0.041401151567697525, 0.010946103371679783, 0.06179419532418251, -0.05453921854496002, -0.0035872941371053457, -0.014343843795359135, 0.06073237210512161, 0.04335511848330498, 0.05227520316839218, -0.021961215883493423, 0.04054080694913864, -0.036841463297605515, 0.001111117540858686, -0.07015755027532578, 0.02227068692445755, -0.023997049778699875, 0.004592555109411478, -0.027379591017961502, -0.012586595490574837, 0.005174302961677313, 0.07447806000709534, 0.03497768193483353, 0.04882306605577469, -0.024578675627708435, 0.0098767951130867, -0.07619176059961319, 0.011508282274007797, -0.02221069298684597, 0.004675252363085747, 0.04716762900352478, 0.029784195125102997, 0.022414131090044975, -0.0068364376202225685, 0.021095212548971176, -0.03183560445904732, -0.006284043192863464, -0.07713968306779861, 0.017821483314037323, 0.009636081755161285, 0.0021402540151029825, 0.012679056264460087, -0.0067688035778701305, -0.027882620692253113, -0.018589714542031288, 0.017958540469408035, 0.0218680240213871, 0.06631388515233994, -0.01703810691833496, -0.036573175340890884, -0.02782438136637211, -0.013364951126277447, -0.004244890529662371, 0.024656791239976883, 0.034704919904470444, 0.029144328087568283, -0.01094831246882677, 0.038376275449991226, 0.030921736732125282, 0.006365236826241016, -0.015436384826898575, -0.0023956752847880125, -0.00609811395406723, -0.00018922198796644807, -0.04601144418120384, -0.011781256645917892, -0.049023956060409546, -0.032089151442050934, -0.036798302084207535, 0.04273199290037155, -0.019120942801237106, -0.046209920197725296, -0.028881503269076347, 0.017477650195360184, -0.06324482709169388, -0.034215956926345825, -0.011763028800487518, 0.022443516179919243, 0.055615659803152084, -0.021527543663978577, -0.012699865736067295, -0.033952437341213226, 0.036792658269405365, 0.010067219845950603, 0.013420278206467628, -0.05610206350684166, -0.0190742090344429, -0.021862417459487915, 0.037627000361680984, 0.0019163641845807433, -0.009671524167060852, 0.06171651557087898, 0.030609045177698135, 0.007647328078746796, 0.039807893335819244, -0.019743211567401886, 0.024735523387789726, 0.07012273371219635, -0.015724141150712967, 0.002786988625302911, -0.014348738826811314, -0.03031267039477825, -0.01910305954515934, 0.010832446627318859, 0.025616958737373352, -0.013498607091605663, 0.035164982080459595, -0.030525410547852516, -0.09259252995252609, 0.011344512924551964, 0.0448492206633091, 0.009511807933449745, -0.017192943021655083, 0.0009959919843822718, -0.015696315094828606, -0.05203522369265556, 0.03142273798584938, 0.026079827919602394, -0.10176796466112137, 0.048199813812971115, -0.02472594566643238, 0.03561290353536606, 0.007999468594789505, -0.019957564771175385, -0.03506026417016983, -0.05666157603263855, 0.012456677854061127, -0.010251385159790516, -0.05676109343767166, -0.0043294234201312065, -0.02871629409492016, -0.016942603513598442, -0.01975075900554657, 1.782485742296558e-05, 0.01400698907673359, -0.05025145038962364, -0.035319734364748, -0.03604283556342125, 0.030636098235845566, -0.031301259994506836, -0.01525047980248928, 0.01549327652901411, -0.022423310205340385, 0.0009528999216854572, -0.04833154007792473, 0.0036643354687839746, 0.05251818895339966, 0.011494145728647709, -0.01368755754083395, 0.026865629479289055, -0.015771949663758278, 0.019022366032004356, 0.038135774433612823, -0.00592975364997983, -0.015635382384061813, -0.006632642820477486, -0.011615036055445671, -0.013829047791659832, 0.023095175623893738, -0.027086416259407997, 0.0014954257057979703, -0.015635628253221512, 0.07093910872936249, 0.01791311986744404, 0.03825487941503525, -0.018333466723561287, 0.005540212616324425, 0.05518727004528046, -0.08307908475399017, -0.03787117078900337, -0.023684626445174217, -0.046406783163547516, -0.010785119608044624, -0.040610410273075104, 0.00873387698084116, -0.03278181701898575, 0.05751285329461098, 0.022706899791955948, 0.03560233116149902, 0.01510976068675518, -0.04296667128801346, 0.021735796704888344, -0.05284764617681503, -0.024962853640317917, -0.06127230077981949, 0.016807476058602333, 0.03977351635694504, 0.028713982552289963, 0.009627566672861576, -0.03350386023521423, -0.017369763925671577, 0.051172927021980286, -0.03819037228822708, -0.06905686110258102, 0.013483839109539986, 0.015883801504969597, -0.02232499048113823, 0.011140036396682262, -0.03294182941317558, -0.027776140719652176, 0.0037222704850137234, -0.04874380677938461, 0.03558765724301338, -0.0011449034791439772, 0.056194666773080826, -0.03275962173938751, 0.030583009123802185, -0.019624829292297363, -0.004206460434943438, 0.04728612303733826, 0.036852095276117325, -0.056389886885881424, 0.006524228490889072, -0.03932418301701546, 0.06598381698131561, 0.07186300307512283, 0.024303102865815163, -0.022692708298563957, 0.04774545505642891, -0.016957854852080345, -0.04879896342754364, 0.03889359533786774, 0.02650143764913082, -0.00432969955727458, -0.06026379019021988, 0.04395407810807228, 0.014756779186427593, -0.05429518595337868, -0.036875177174806595, 0.020686844363808632, -0.050948116928339005, 0.0014995703240856528, -0.034173790365457535, -0.0029576674569398165, -0.012043935246765614, 0.06271250545978546, 0.020339487120509148, 0.04058345779776573, 0.07969490438699722, -0.013987645506858826, -0.0012916410341858864, -0.011281062848865986, 0.054773397743701935, 0.032378099858760834, 0.014958116225898266, 0.01541866548359394, 0.058016587048769, -0.06051275506615639, -0.06000731140375137, 0.017267679795622826, 0.0009328529122285545, -0.011273013427853584, -0.004955338779836893, -0.037080880254507065, 0.050435904413461685, 0.03723977506160736, 0.05216604471206665, -0.006142789032310247, 0.004147491883486509, 0.006026263348758221, 0.00296843983232975, 0.014912114478647709, 0.013720077462494373, -0.001050621154718101, 0.022351104766130447, -0.034664325416088104, -0.033447470515966415, -0.05729569494724274, -0.009359385818243027, -0.0406610332429409, -0.00486084446310997, 0.0034341730643063784, -0.0007760529406368732, -0.025142356753349304, 0.0005846046260558069, 0.04668072611093521, -0.02234526537358761, 0.015011454001069069, 0.010457988828420639, 0.031889740377664566, -0.0454280823469162, 0.007132984232157469, 0.0156369861215353, -0.030474595725536346, 0.01581236533820629, -0.024940166622400284, 0.038149017840623856, -0.001386476680636406, 0.01456200610846281, 0.014937029220163822, -0.01054649893194437, 0.0014398841885849833, 0.02344362623989582, 0.05515832081437111, -0.05780830979347229, -0.04704444110393524, -0.04500919580459595, -0.0033058670815080404, -0.03994273394346237, -0.01494287233799696, 0.03715193644165993, -0.03630097582936287, -0.0461781844496727, -0.0003109534736722708, -0.02262723632156849, 0.011950724758207798, 0.019442932680249214, -0.04442780464887619, -0.028794994577765465, 0.03229871019721031, -0.008985796011984348, 0.009298265911638737, 0.05928938463330269, 0.09517085552215576, -0.000629143905825913, -0.005049935542047024, -0.0028551898431032896, 0.011517282575368881, 0.06863340735435486, 0.004424599930644035, 0.048147816210985184, -0.03985914587974548, 0.0546540766954422, 0.04547060281038284, 0.023972952738404274, -0.09145636111497879, 0.0831027701497078, -0.040111105889081955, -0.031261835247278214, 0.05955589935183525, 0.029722291976213455, 0.020183593034744263, -0.005242380313575268, -0.013953893445432186, -0.016561711207032204, 0.019141381606459618, 0.028448723256587982, -0.024664301425218582, 0.05918459966778755, 0.03784049674868584, 0.03316793963313103, 0.003169242525473237, 0.04082033038139343, 0.0081052016466856, -0.015369432978332043, -0.016413867473602295, -0.019344067201018333, -0.03648652508854866, -0.11166073381900787, -0.013331728987395763, 0.00018163752974942327, 1.0881681191676762e-06, -0.05642422288656235, 0.009510340169072151, 0.006848383694887161, 0.004350434057414532, 0.013067587278783321, 0.004298544488847256, -0.0008969894261099398, -0.04666737839579582, -0.06356147676706314, -0.0531609021127224, -0.00593556696549058, 0.014823823235929012, -0.04410639405250549, 0.03196171671152115, -0.0517844632267952, 0.03002982772886753, -0.011110503226518631, -0.0112466374412179, 0.021627968177199364, 0.025990985333919525, 0.01305512897670269]}